stridessequencefinder/README.MD
stridessequencefinder/__init__.py
stridessequencefinder/requirements.txt
stridessequencefinder/thirdparty.json
stridessequencefinder-0.10.dist-info/LICENSE.rst
stridessequencefinder-0.10.dist-info/METADATA
stridessequencefinder-0.10.dist-info/WHEEL
stridessequencefinder-0.10.dist-info/top_level.txt
stridessequencefinder-0.10.dist-info/RECORD
