Metadata-Version: 2.1
Name: stridessequencefinder
Version: 0.10
Summary: finds sequences [3, 4, 5] in NumPy arrays [1, 2, 3, 4, 5, 1, 2, 3, 4, 5] - result: [2 7]
Home-page: https://github.com/hansalemaos/stridessequencefinder
Author: Johannes Fischer
Author-email: aulasparticularesdealemaosp@gmail.com
License: MIT
Keywords: numpy,numexpr,strides,sequence
Classifier: Development Status :: 4 - Beta
Classifier: Programming Language :: Python :: 3 :: Only
Classifier: Programming Language :: Python :: 3.10
Classifier: Topic :: Software Development :: Libraries :: Python Modules
Classifier: Topic :: Utilities
License-File: LICENSE.rst
Requires-Dist: numexpr
Requires-Dist: numpy
